sslcrypto/__init__.py
sslcrypto/_aes.py
sslcrypto/_ecc.py
sslcrypto/_ripemd.py
sslcrypto/fallback/__init__.py
sslcrypto/fallback/_jacobian.py
sslcrypto/fallback/_util.py
sslcrypto/fallback/aes.py
sslcrypto/fallback/ecc.py
sslcrypto/fallback/rsa.py
sslcrypto/openssl/__init__.py
sslcrypto/openssl/aes.py
sslcrypto/openssl/discovery.py
sslcrypto/openssl/ecc.py
sslcrypto/openssl/library.py
sslcrypto/openssl/rsa.py
test/__init__.py
test/conf.py
test/test_aes.py
test/test_basic.py
test/test_ecc_arithmetic.py
test/test_ecdsa_signing.py
test/test_thread_safety.py
sslcrypto-5.3.dist-info/LICENSE
sslcrypto-5.3.dist-info/METADATA
sslcrypto-5.3.dist-info/WHEEL
sslcrypto-5.3.dist-info/top_level.txt
sslcrypto-5.3.dist-info/RECORD
