Metadata-Version: 2.1
Name: sslcrypto
Version: 5.3
Summary: ECIES, AES and RSA OpenSSL-based implementation with fallback
Home-page: https://github.com/imachug/sslcrypto
Author: Ivanq
Author-email: imachug@gmail.com
License: UNKNOWN
Platform: UNKNOWN
